hnswlib4vis.cpython-38-darwin.so
hnswlib4vis-1.0.0.dist-info/LICENSE
hnswlib4vis-1.0.0.dist-info/METADATA
hnswlib4vis-1.0.0.dist-info/WHEEL
hnswlib4vis-1.0.0.dist-info/top_level.txt
hnswlib4vis-1.0.0.dist-info/RECORD
